LICENSE
MANIFEST.in
README.md
setup.py
gpus/__init__.py
gpus/__main__.py
gpus/app.py
gpus/cli.py
gpus/cloud_client.py
gpus/gpu_stats.py
gpus.egg-info/PKG-INFO
gpus.egg-info/SOURCES.txt
gpus.egg-info/dependency_links.txt
gpus.egg-info/entry_points.txt
gpus.egg-info/requires.txt
gpus.egg-info/top_level.txt
gpus/static/css/style.css
gpus/static/js/app.js
gpus/templates/index.html