Metadata-Version: 2.2
Name: gpus
Version: 0.2.0
Summary: A web interface for monitoring NVIDIA GPUs
Home-page: https://github.com/fakerybakery/gpus
Author: mrfakename
Author-email: me@mrfake.name
License: MIT
Classifier: Programming Language :: Python :: 3
Classifier: License :: OSI Approved :: MIT License
Classifier: Operating System :: OS Independent
Requires-Python: >=3.6
License-File: LICENSE
Requires-Dist: nvidia-ml-py
Requires-Dist: click
Requires-Dist: flask
Requires-Dist: flask-socketio
Requires-Dist: eventlet>=0.30.0
Requires-Dist: python-engineio>=4.0.0
Requires-Dist: python-socketio>=5.0.0
Requires-Dist: psutil
Requires-Dist: rich>=10.0.0
Requires-Dist: requests>=2.25.0
Dynamic: author
Dynamic: author-email
Dynamic: classifier
Dynamic: description
Dynamic: description-content-type
Dynamic: home-page
Dynamic: license
Dynamic: requires-dist
Dynamic: requires-python
Dynamic: summary
